{
    "refs": [
        {
"category": null,
"text": "Bartens, Angela. 2011. Substrate features in Nicaraguan, Providence and San Andrés Creole Englishes: A comparison with Twi. In Lefebvre, Claire (ed.), Creoles, their substrates, and language typology, 201-224. Amsterdam: Benjamins.",
"html": "<p><span>Bartens, Angela. 2011. Substrate features in Nicaraguan, Providence and San Andrés Creole Englishes: A comparison with Twi. In Lefebvre, Claire (ed.), Creoles, their substrates, and language typology, 201-224. Amsterdam: Benjamins.</span></p>",
"id": "bartens2011",
"key": "Bartens 2011"
},
        {
            "category": null, 
            "text": "Bartens, Angela. 2012. Substrate features in Nicaraguan, Providence and San Andr\u00e9s Creole Englishes: A comparison with Twi. In: Lefebvre, Claire (ed.) 2012. Creoles, their substrates, and language typology. Amsterdam: Benjamins, 201-224.", 
            "html": "<p class=\"western c24\" lang=\"en-GB\" xml:lang=\"en-GB\"><span class=\"c19\" lang=\"en-US\" xml:lang=\"en-US\">Bartens, Angela. 2012.\nSubstrate features in Nicaraguan, Providence and San Andr\u00e9s Creole\nEnglishes: A comparison with Twi. In: Lefebvre, Claire (ed.)\n2012.</span> <span class=\"c23\" lang=\"en-US\" xml:lang=\"en-US\">Creoles, their substrates, and language typology.</span>\n<span class=\"c19\" lang=\"en-US\" xml:lang=\"en-US\">Amsterdam:\nBenjamins, 201-224.</span></p>", 
            "id": "bartens2012", 
            "key": "Bartens 2012"
        }, 
        {
            "category": null, 
            "text": "Daniel, Michael & Spencer, Andrew. 2009. The vocative \u2013 an outlier case. In: Malchukov, Andrej & Spencer, Andrew (eds.) The Oxford handbook of case. Oxford: Oxford University Press, 626-634.", 
            "html": "<p class=\"western c24\" lang=\"en-GB\" xml:lang=\"en-GB\"><span class=\"c19\" lang=\"en-US\" xml:lang=\"en-US\">Daniel, Michael &amp; Spencer,\nAndrew. 2009. The vocative \u2013 an outlier case. In: Malchukov, Andrej\n&amp; Spencer, Andrew (eds.)</span> <span class=\"c23\" lang=\"en-US\" xml:lang=\"en-US\">The Oxford handbook of case.</span> <span class=\"c19\" lang=\"en-US\" xml:lang=\"en-US\">Oxford: Oxford University\nPress, 626-634.</span></p>", 
            "id": "danielspencer2009", 
            "key": "Daniel & Spencer 2009"
        }, 
        {
            "category": null, 
            "text": "Rowlands, E. C. 1969. Teach yourself Yoruba. London: Hodder and Stoughton.", 
            "html": "<p class=\"western c24\" lang=\"en-GB\" xml:lang=\"en-GB\"><span class=\"c19\" lang=\"en-US\" xml:lang=\"en-US\">Rowlands, E. C. 1969.</span>\n<span class=\"c23\" lang=\"en-US\" xml:lang=\"en-US\">Teach yourself\nYoruba.</span> <span class=\"c19\" lang=\"en-US\" xml:lang=\"en-US\">London: Hodder and Stoughton.</span></p>", 
            "id": "rowlands1969", 
            "key": "Rowlands 1969"
        }
    ], 
    "outline": [
        [
            "1. Vocative phrases and vocative markers", 
            "section-1vocativephrasesandvocativemarkers"
        ], 
        [
            "2. Optional vocative marker preceding noun", 
            "section-2optionalvocativemarkerprecedingnoun"
        ], 
        [
            "3. Optional vocative marker following noun", 
            "section-3optionalvocativemarkerfollowingnoun"
        ], 
        [
            "4. Optional vocative markers in both positions", 
            "section-4optionalvocativemarkersinbothpositions"
        ], 
        [
            "5. Obligatory vocative marker", 
            "section-5obligatoryvocativemarker"
        ]
    ], 
    "authors": []
}
