{
    "refs": [
        {
            "category": null, 
            "text": "Corbett Greville C. 2005a: WALS feature 30", 
            "html": "<p class=\"western c34\">Corbett Greville C. 2005a: WALS feature\n30</p>", 
            "id": "b5b3e08c9d4f04de8011109709abc4dc", 
            "key": null
        }, 
        {
            "category": null, 
            "text": "Corbett, Greville C. 2005b: Wals feature 31", 
            "html": "<p class=\"western c34\">Corbett, Greville C. 2005b: Wals feature\n31</p>", 
            "id": "9142a62b5ebe53c9e39ab0bebc1929e3", 
            "key": null
        }, 
        {
            "category": null, 
            "text": "Corbett, Greville C. 2005c: Wals feature 32", 
            "html": "<p class=\"western c34\">Corbett, Greville C. 2005c: Wals feature\n32</p>", 
            "id": "649bdb7b0115a206fc1ef08e6bff8c2b", 
            "key": null
        }
    ], 
    "outline": [
        [
            "1. Introduction", 
            "section-1introduction"
        ], 
        [
            "2. The values", 
            "section-2thevalues"
        ]
    ], 
    "authors": []
}