{
    "refs": [
        {
            "category": null, 
            "text": "Arends, Jacques & Muysken, Pieter & Smith, Norval (eds.). 1995. Pidgins and creoles: An introduction. Amsterdam: Benjamins.", 
            "html": "<p class=\"western\" style=\"margin-bottom: 0in\">Arends,\n\nJacques &amp; Muysken, Pieter &amp; Smith, Norval (eds.). 1995.\n\n<i>Pidgins and\n\ncreoles: An introduction</i>.\n\nAmsterdam: Benjamins.</p>", 
            "id": "arendsmuyskensmith1995", 
            "key": "Arends & Muysken & Smith 1995"
        }, 
        {
            "category": null, 
            "text": "Bickerton, Derek. 1981. Roots of Languages. Ann Arbor: Karoma.", 
            "html": "<p class=\"western\" style=\"margin-bottom: 0in\">Bickerton,\n\nDerek. 1981. <i>Roots\n\nof Languages</i>. Ann\n\nArbor: Karoma.</p>", 
            "id": "bickerton1981", 
            "key": "Bickerton 1981"
        }, 
        {
            "category": null, 
            "text": "Holm, John. 1984. Variability of the copula in Black English and its creole kin. American Speech 59:291-309.", 
            "html": "<p class=\"western\" style=\"margin-bottom: 0in\">Holm,\n\nJohn. 1984. Variability of the copula in Black English and its creole\n\nkin. <i>American\n\nSpeech</i> 59:291-309.</p>", 
            "id": "holm1984", 
            "key": "Holm 1984"
        }, 
        {
            "category": null, 
            "text": "Rickford, John R. 1998. The creole origins of African- American Vernacular English: Evidence from copula absence. In: Mufwene, Salikoko & Rickford, John R. & Bailey, Guy & Baugh, John (eds). African-American English: Structure, history, use. London: Routledge.", 
            "html": "<p class=\"western\" style=\"margin-bottom: 0in\">Rickford,\n\nJohn R. 1998. The creole origins of African- American Vernacular\n\nEnglish: Evidence from copula absence.  In: Mufwene, Salikoko &amp;\n\nRickford, John R. &amp; Bailey, Guy &amp; Baugh, John (eds).\n\nAfrican-American English: Structure, history, use. London: Routledge.</p>", 
            "id": "rickford1998", 
            "key": "Rickford 1998"
        }, 
        {
            "category": null, 
            "text": "Sharma, Devyani & Rickford, John R. 2009. AAVE/Creole copula absence: A critique of the imperfect learning hypothesis. Journal of Pidgin and Creole Languages 24 (1): 2009, 53-90.", 
            "html": "<p class=\"western\" style=\"margin-bottom: 0in\">Sharma,\n\nDevyani &amp; Rickford, John R. 2009. AAVE/Creole copula absence: A\n\ncritique of the imperfect learning hypothesis. Journal of Pidgin and\n\nCreole Languages 24 (1): 2009, 53-90.</p>", 
            "id": "sharmarickford2009", 
            "key": "Sharma & Rickford 2009"
        }, 
        {
            "category": null, 
            "text": "Stassen, Leon. 2005c. Nominal and Locational Predication. In: WALS.", 
            "html": "<p class=\"western\" style=\"margin-bottom: 0in\">Stassen,\n\nLeon. 2005c. Nominal and Locational Predication. In: WALS.</p>", 
            "id": "stassen2005c", 
            "key": "Stassen 2005c"
        },
        {
"category": null,
"text": "Winford, Donald. 1993. Predication in Caribbean English Creoles. (Creole Language Library 10.) Amsterdam: John Benjamins.",
"html": "<p class=\"ReferencetitlesCxSpMiddle\" style=\"margin-top:0cm;marginright:45.0pt;margin-bottom:0cm;margin-left:14.2pt;margin-bottom:.0001pt;text-indent:-14.2pt;lineheight:150%\"><span>Winford, Donald. 1993. Predication in Caribbean English Creoles. (Creole Language Library 10.) Amsterdam: John Benjamins.</span></p>",
"id": "winford1993",
"key": "Winford 1993"
}, 
        {
"category": null,
"text": "Boretzky, Norbert. 1983. Kreolsprachen, Substrate und Sprachwandel. Wiesbaden: Harrassowitz.",
"html": "<p class=\"ReferencetitlesCxSpMiddle\" style=\"margin-top:0cm;marginright:45.0pt;margin-bottom:0cm;margin-left:14.2pt;margin-bottom:.0001pt;text-indent:-14.2pt;lineheight:150%\"><span>Boretzky, Norbert. 1983. Kreolsprachen, Substrate und Sprachwandel. Wiesbaden: Harrassowitz.</span></p>",
"id": "boretzky1983",
"key": "Boretzky 1983"
}
    ], 
    "outline": [
        [
            "1. Introduction",
            "section-1introduction"
        ],
        [
            "2. The values",
            "section-2thevalues"
        ],
        [
            "3. Distribution",
            "section-3distribution"
        ]
    ],
    "authors": []
}
